{
  "name": "Vibe Bot",
  "version": "2.1.0",
  "author": "Airis",
  "license": "Proprietary - All Rights Reserved",
  "description": "A feature-rich Discord bot with 200+ commands, built live on Twitch with the community",
  "website": "https://github.com/Sentinelbot-official/vibebot",
  "support_server": "DISCORD_SERVER_COMING_SOON",
  "twitch": "https://twitch.tv/projectdraguk",
  "invite_link": "https://discord.com/api/oauth2/authorize?client_id=YOUR_BOT_ID_HERE&permissions=8&scope=bot",
  "repository_notice": "Proprietary software. Forking for contributions is allowed. Public redistribution or hosting requires permission.",
  "features": [
    "Advanced Moderation (23 commands)",
    "Economy System (25+ commands with trading, stocks, property, crafting)",
    "Leveling & XP (4 commands + voice XP tracking)",
    "Social Features (7 commands: marriage, reputation, profiles)",
    "Mini-Games (25+ games: Hangman, Wordle, Blackjack, Pet System)",
    "Reaction & Button Roles",
    "Auto-Moderation & Anti-Raid (spam, links, word filters, regex)",
    "Giveaways & Engagement",
    "Utility Commands (51+ commands with API integrations)",
    "Fun Commands (25+ commands)",
    "Admin Tools (30+ commands)",
    "Ticket, Verification & Modmail Systems",
    "Voice Activity Tracking & Stats",
    "Server Analytics & Insights",
    "Premium/VIP System",
    "Temporary Voice Channels",
    "Achievements & Badges",
    "Internationalization (i18n)",
    "Auto-Backup & Health Monitoring",
    "Custom Per-Server Settings"
  ],
  "colors": {
    "primary": "#0099ff",
    "success": "#00ff00",
    "warning": "#ffa500",
    "error": "#ff0000",
    "economy": "#ffd700"
  }
}
